sqlspec/__init__.py
sqlspec/__main__.py
sqlspec/__metadata__.py
sqlspec/_serialization.py
sqlspec/_typing.py
sqlspec/base.py
sqlspec/cli.py
sqlspec/config.py
sqlspec/exceptions.py
sqlspec/loader.py
sqlspec/protocols.py
sqlspec/py.typed
sqlspec/typing.py
sqlspec/adapters/__init__.py
sqlspec/adapters/adbc/__init__.py
sqlspec/adapters/adbc/_typing.py
sqlspec/adapters/adbc/config.py
sqlspec/adapters/adbc/core.py
sqlspec/adapters/adbc/data_dictionary.py
sqlspec/adapters/adbc/driver.py
sqlspec/adapters/adbc/type_converter.py
sqlspec/adapters/adbc/adk/__init__.py
sqlspec/adapters/adbc/adk/store.py
sqlspec/adapters/adbc/events/__init__.py
sqlspec/adapters/adbc/events/store.py
sqlspec/adapters/adbc/litestar/__init__.py
sqlspec/adapters/adbc/litestar/store.py
sqlspec/adapters/aiosqlite/__init__.py
sqlspec/adapters/aiosqlite/_typing.py
sqlspec/adapters/aiosqlite/config.py
sqlspec/adapters/aiosqlite/core.py
sqlspec/adapters/aiosqlite/data_dictionary.py
sqlspec/adapters/aiosqlite/driver.py
sqlspec/adapters/aiosqlite/pool.py
sqlspec/adapters/aiosqlite/adk/__init__.py
sqlspec/adapters/aiosqlite/adk/store.py
sqlspec/adapters/aiosqlite/events/__init__.py
sqlspec/adapters/aiosqlite/events/store.py
sqlspec/adapters/aiosqlite/litestar/__init__.py
sqlspec/adapters/aiosqlite/litestar/store.py
sqlspec/adapters/asyncmy/__init__.py
sqlspec/adapters/asyncmy/_typing.py
sqlspec/adapters/asyncmy/config.py
sqlspec/adapters/asyncmy/core.py
sqlspec/adapters/asyncmy/data_dictionary.py
sqlspec/adapters/asyncmy/driver.py
sqlspec/adapters/asyncmy/adk/__init__.py
sqlspec/adapters/asyncmy/adk/store.py
sqlspec/adapters/asyncmy/events/__init__.py
sqlspec/adapters/asyncmy/events/store.py
sqlspec/adapters/asyncmy/litestar/__init__.py
sqlspec/adapters/asyncmy/litestar/store.py
sqlspec/adapters/asyncpg/__init__.py
sqlspec/adapters/asyncpg/_typing.py
sqlspec/adapters/asyncpg/config.py
sqlspec/adapters/asyncpg/core.py
sqlspec/adapters/asyncpg/data_dictionary.py
sqlspec/adapters/asyncpg/driver.py
sqlspec-0.36.1.dist-info/METADATA
sqlspec-0.36.1.dist-info/WHEEL
sqlspec-0.36.1.dist-info/entry_points.txt
sqlspec-0.36.1.dist-info/licenses/LICENSE
sqlspec-0.36.1.dist-info/RECORD
