Metadata-Version: 2.4
Name: sqlspec
Version: 0.36.1
Summary: SQL Experiments in Python
Project-URL: Discord, https://discord.gg/litestar
Project-URL: Issue, https://github.com/litestar-org/sqlspec/issues/
Project-URL: Source, https://github.com/litestar-org/sqlspec
Author-email: Cody Fincher <cody@litestar.dev>
Maintainer-email: Litestar Developers <hello@litestar.dev>
License-Expression: MIT
License-File: LICENSE
Requires-Python: <4.0,>=3.10
Requires-Dist: mypy-extensions
Requires-Dist: rich-click>=1.9.0
Requires-Dist: sqlglot>=19.9.0
Requires-Dist: tomli>=2.0.0; python_version < '3.11'
Requires-Dist: typing-extensions
Provides-Extra: adbc
Requires-Dist: adbc-driver-manager; extra == 'adbc'
Requires-Dist: pyarrow; extra == 'adbc'
Provides-Extra: adk
Requires-Dist: google-adk; extra == 'adk'
Provides-Extra: aioodbc
Requires-Dist: aioodbc; extra == 'aioodbc'
Provides-Extra: aiosqlite
Requires-Dist: aiosqlite; extra == 'aiosqlite'
Provides-Extra: alloydb
Requires-Dist: google-cloud-alloydb-connector; extra == 'alloydb'
Provides-Extra: asyncmy
Requires-Dist: asyncmy; extra == 'asyncmy'
Provides-Extra: asyncpg
Requires-Dist: asyncpg; extra == 'asyncpg'
Provides-Extra: attrs
Requires-Dist: attrs; extra == 'attrs'
Requires-Dist: cattrs; extra == 'attrs'
Provides-Extra: bigquery
Requires-Dist: google-cloud-bigquery; extra == 'bigquery'
Requires-Dist: google-cloud-storage; extra == 'bigquery'
Provides-Extra: cloud-sql
Requires-Dist: cloud-sql-python-connector; extra == 'cloud-sql'
Provides-Extra: cockroachdb
Requires-Dist: asyncpg; extra == 'cockroachdb'
Requires-Dist: psycopg[binary,pool]; extra == 'cockroachdb'
Provides-Extra: duckdb
Requires-Dist: duckdb; extra == 'duckdb'
Provides-Extra: fastapi
Requires-Dist: fastapi; extra == 'fastapi'
Provides-Extra: flask
Requires-Dist: flask; extra == 'flask'
Provides-Extra: fsspec
Requires-Dist: fsspec; extra == 'fsspec'
Provides-Extra: litestar
Requires-Dist: litestar; extra == 'litestar'
Provides-Extra: msgspec
Requires-Dist: msgspec; extra == 'msgspec'
Provides-Extra: mypyc
Provides-Extra: mysql-connector
Requires-Dist: mysql-connector-python; extra == 'mysql-connector'
Provides-Extra: nanoid
Requires-Dist: fastnanoid>=0.4.1; extra == 'nanoid'
Provides-Extra: obstore
Requires-Dist: obstore; extra == 'obstore'
Provides-Extra: opentelemetry
Requires-Dist: opentelemetry-instrumentation; extra == 'opentelemetry'
Provides-Extra: oracledb
Requires-Dist: oracledb; extra == 'oracledb'
Provides-Extra: orjson
Requires-Dist: orjson; extra == 'orjson'
Provides-Extra: pandas
Requires-Dist: pandas; extra == 'pandas'
Requires-Dist: pyarrow; extra == 'pandas'
Provides-Extra: performance
Requires-Dist: msgspec; extra == 'performance'
Requires-Dist: sqlglot[rs]; extra == 'performance'
Provides-Extra: polars
Requires-Dist: polars; extra == 'polars'
Requires-Dist: pyarrow; extra == 'polars'
Provides-Extra: prometheus
Requires-Dist: prometheus-client; extra == 'prometheus'
Provides-Extra: psqlpy
Requires-Dist: psqlpy; extra == 'psqlpy'
Provides-Extra: psycopg
Requires-Dist: psycopg[binary,pool]; extra == 'psycopg'
Provides-Extra: pydantic
Requires-Dist: pydantic; extra == 'pydantic'
Requires-Dist: pydantic-extra-types; extra == 'pydantic'
Provides-Extra: pymssql
Requires-Dist: pymssql; extra == 'pymssql'
Provides-Extra: pymysql
Requires-Dist: pymysql; extra == 'pymysql'
Provides-Extra: spanner
Requires-Dist: google-cloud-spanner; extra == 'spanner'
Provides-Extra: uuid
Requires-Dist: uuid-utils; extra == 'uuid'
